cartosky/__init__.py
cartosky/_version.py
cartosky/constants.py
cartosky/core.py
cartosky/crs.py
cartosky/healpix.py
cartosky/proj.py
cartosky/skyaxes.py
cartosky/survey.py
cartosky/utils.py
cartosky/zoom.py
cartosky/data/bliss-poly.txt
cartosky/data/ccd_corners_xy_fill.dat
cartosky/data/decals-poly.txt
cartosky/data/derosita-poly.txt
cartosky/data/des-round13-poly.txt
cartosky/data/des-round17-poly.txt
cartosky/data/macho_corners_xy.dat
cartosky/data/maglites-poly.txt
cartosky/data/smash_fields_final.txt
cartosky/instrument/__init__.py
cartosky/instrument/camera.py
cartosky/instrument/decam.py
cartosky/instrument/macho.py
cartosky-0.1.dist-info/LICENSE
cartosky-0.1.dist-info/METADATA
cartosky-0.1.dist-info/WHEEL
cartosky-0.1.dist-info/top_level.txt
cartosky-0.1.dist-info/RECORD
